{
  "items": [
    {
      "title": "6 כיסאות פינת אוכל",
      "image": "dinning_chair.png",
      "price": "100 ש''ח לכסא",
      "readyAt": "now",
      "text": [
        "6 כסאות פינת אוכל",
        "בקניה של כל ה-6 העלות היא 500 ש''ח"
      ]
    },
    {
      "title": "מכונת נספרסו + מקציף",
      "image": "nespresso.png",
      "price": "450 ש''ח",
      "readyAt": "june",
      "text": [
        "מכונת נספרסו דגם פיקסי",
        "צבע אדום",
        "כולל מקציף חלב ארוצ'ינו"
      ]
    },
    {
      "title": "ריהוט מרפסת - איקאה",
      "image": "balcony.jpg",
      "price": "1500 ש''ח",
      "readyAt": "now",
      "text": [
        "ריהוט מרפסת איקאה",
        "סך הכל 6 מושבים"
      ],
      "link": "https://ikea.co.il/catalogue/Outdoor/Outdoor_lounge_furniture/39260940"
    },
    {
      "title": "כוסות אלכוהול",
      "image": "glasses.png",
      "price": "10 ש''ח ליחידה",
      "readyAt": "now",
      "text": [
        "- כוסות לונגים סטולי - 8 יחידות",
        "- כוסיות שוטים סטולי - 11 יחידות",
        "- כוסות יין קטנות יקב ירדן - 4 יחידות",
        "- כוסות שוטים גבוהות - 6 יחידות"
      ]
    },
    {
      "title": "ארון מדפים גבוה",
      "image": "bookshelf_2.png",
      "price": "50 ש''ח",
      "readyAt": "now",
      "text": [
        "גובה - 220 ס''מ",
        "רוחב - 43 ס''מ",
        "עומק - 30 ס''מ"
      ]
    },
    {
      "title": "מקרר 490 ליטר",
      "image": "refrigirator.png",
      "price": "1500 ש''ח",
      "readyAt": "june",
      "text": [
        "רוחב 78 ס''מ",
        "עומק 70 ס''מ",
        "גובה 170 ס''מ",
        "מקפיא - 140 ליטר",
        "מקרר - 350 ליטר"
      ]
    },
    {
      "title": "מכונת כביסה 8 ק''ג",
      "image":  "washing_machine.jpg",
      "price": "1500 ש''ח",
      "readyAt": "june",
      "text": [
        "מכונת כביסה של חברת קונסטרוקטה",
        "יכולת כיבוס עד 8 ק''ג"
      ]
    },
    {
      "title": "ארונית למכונת כביסה",
      "image":  "washing_machine_closet.jpg",
      "price": "100 ש''ח",
      "readyAt": "june",
      "text": [
        "ארונית למכונת כביסה",
        "גובה ברוטו - 190 ס''מ",
        "גובה ארון - 100 ס''מ",
        "רוחב תא למכונת כביסה - 60 ס''מ"
      ],
      "link": "https://ikea.co.il/catalogue/Bathroom/Bathroom_furniture/00206096"
    },
    {
      "title": "שולחן כתיבה/עבודה איקאה",
      "image":  "ikea_table_1.jpg",
      "price": "100 ש''ח לשולחן",
      "readyAt": "june",
      "text": [
        "שולחן כתיבה/עבודה איקאה",
        "גובה - 74 ס''מ",
        "רוחב - 120 ס''מ",
        "עומק - 60 ס''מ",
        "יש 2 שולחנות (המחיר הוא לשולחן)"
      ]
    },
    {
      "title": "שולחן כתיבה/עבודה איקאה פינתי",
      "image":  "ikea_table_2.jpg",
      "price": "100 ש''ח",
      "readyAt": "june",
      "text": [
        "שולחן כתיבה/עבודה איקאה פינתי",
        "גובה - 74 ס''מ",
        "רוחב - 120 ס''מ",
        "אורך - 120 ס''מ",
        "עומק - 60 ס''מ"
      ]
    },
    {
      "title": "ארונית מגירות קטנה",
      "image":  "shida_1.png",
      "price": "150 ש''ח",
      "readyAt": "now",
      "text": [
        "ארונית מגירות קטנה איקאה"
      ]
    },
    {
      "title": "כיסא בטיחות צי'קו",
      "image":  "safety_seat.png",
      "price": "400 ש''ח",
      "readyAt": "now",
      "text": [
        "כיסא בטיחות צ'יקו",
        "כולל איזופיקס",
        "צבע אדום",
        "בתוקף עד 2025"
      ]
    }
  ]
}
